ceteris_paribus/__init__.py
ceteris_paribus/explainer.py
ceteris_paribus/gower.py
ceteris_paribus/profiles.py
ceteris_paribus/select_data.py
ceteris_paribus/utils.py
ceteris_paribus/datasets/__init__.py
ceteris_paribus/datasets/insurance.csv
ceteris_paribus/datasets/titanic_train.csv
ceteris_paribus/plots/__init__.py
ceteris_paribus/plots/ceterisParibusD3.js
ceteris_paribus/plots/plot_template.html
ceteris_paribus/plots/plots.py
jupyter-notebooks/__init__.py
pyCeterisParibus-0.5.1.dist-info/LICENSE
pyCeterisParibus-0.5.1.dist-info/METADATA
pyCeterisParibus-0.5.1.dist-info/WHEEL
pyCeterisParibus-0.5.1.dist-info/top_level.txt
pyCeterisParibus-0.5.1.dist-info/RECORD
