Metadata-Version: 2.1
Name: pyCeterisParibus
Version: 0.5.1
Summary: Ceteris Paribus python package
Home-page: https://github.com/ModelOriented/pyCeterisParibus
Author: Michał Kuźba
Author-email: michal.kuzba@students.mimuw.edu.pl
License: UNKNOWN
Platform: UNKNOWN
Classifier: Intended Audience :: Science/Research
Classifier: Intended Audience :: Developers
Classifier: License :: OSI Approved :: Apache Software License
Classifier: Operating System :: OS Independent
Classifier: Programming Language :: Python :: 3
Classifier: Programming Language :: Python :: 3.5
Classifier: Programming Language :: Python :: 3.6
Classifier: Programming Language :: Python :: 3.7
Classifier: Topic :: Scientific/Engineering :: Artificial Intelligence
Classifier: Topic :: Scientific/Engineering :: Visualization
Requires-Dist: Flask (>=1.0.2)
Requires-Dist: numpy (>=1.15.4)
Requires-Dist: pandas (>=0.23.4)
